qctoolkit/__init__.py
qupulse/__init__.py
qupulse/__init__.pyi
qupulse/comparable.py
qupulse/parameter_scope.py
qupulse/plotting.py
qupulse/serialization.py
qupulse/_program/__init__.py
qupulse/_program/_loop.py
qupulse/_program/tabor.py
qupulse/_program/transformation.py
qupulse/_program/volatile.py
qupulse/_program/waveforms.py
qupulse/expressions/__init__.py
qupulse/expressions/protocol.py
qupulse/expressions/sympy.py
qupulse/expressions/wrapper.py
qupulse/hardware/__init__.py
qupulse/hardware/setup.py
qupulse/hardware/util.py
qupulse/hardware/awgs/__init__.py
qupulse/hardware/awgs/base.py
qupulse/hardware/awgs/dummy.py
qupulse/hardware/awgs/tabor.py
qupulse/hardware/awgs/tektronix.py
qupulse/hardware/awgs/zihdawg.py
qupulse/hardware/dacs/__init__.py
qupulse/hardware/dacs/alazar.py
qupulse/hardware/dacs/alazar2.py
qupulse/hardware/dacs/dac_base.py
qupulse/hardware/dacs/dummy.py
qupulse/hardware/feature_awg/__init__.py
qupulse/hardware/feature_awg/base.py
qupulse/hardware/feature_awg/base_features.py
qupulse/hardware/feature_awg/channel_tuple_wrapper.py
qupulse/hardware/feature_awg/features.py
qupulse/hardware/feature_awg/tabor.py
qupulse/program/__init__.py
qupulse/program/linspace.py
qupulse/program/loop.py
qupulse/program/transformation.py
qupulse/program/volatile.py
qupulse/program/waveforms.py
qupulse/pulses/__init__.py
qupulse/pulses/abstract_pulse_template.py
qupulse/pulses/arithmetic_pulse_template.py
qupulse/pulses/constant_pulse_template.py
qupulse/pulses/function_pulse_template.py
qupulse/pulses/interpolation.py
qupulse/pulses/loop_pulse_template.py
qupulse/pulses/mapping_pulse_template.py
qupulse/pulses/measurement.py
qupulse/pulses/multi_channel_pulse_template.py
qupulse/pulses/parameters.py
qupulse/pulses/plotting.py
qupulse/pulses/point_pulse_template.py
qupulse/pulses/pulse_template.py
qupulse/pulses/pulse_template_parameter_mapping.py
qupulse/pulses/range.py
qupulse/pulses/repetition_pulse_template.py
qupulse/pulses/sequence_pulse_template.py
qupulse-0.10.dist-info/licenses/LICENSE
qupulse-0.10.dist-info/METADATA
qupulse-0.10.dist-info/WHEEL
qupulse-0.10.dist-info/top_level.txt
qupulse-0.10.dist-info/RECORD
