Metadata-Version: 2.4
Name: qupulse
Version: 0.10
Summary: A Quantum compUting PULse parametrization and SEquencing framework
Home-page: https://github.com/qutech/qupulse
Author: Quantum Technology Group and Chair of Software Engineering, RWTH Aachen University
License: MIT
Keywords: quantum,physics,control pulse,qubit
Classifier: Programming Language :: Python :: 3
Classifier: License :: OSI Approved :: MIT License
Classifier: Operating System :: OS Independent
Classifier: Topic :: Scientific/Engineering
Classifier: Intended Audience :: Science/Research
Requires-Python: >=3.8
License-File: LICENSE
Requires-Dist: sympy>=1.1.1
Requires-Dist: numpy
Requires-Dist: cached_property; python_version < "3.8"
Requires-Dist: typing-extensions; python_version < "3.8"
Requires-Dist: frozendict
Requires-Dist: lazy_loader
Provides-Extra: tests
Requires-Dist: pytest; extra == "tests"
Requires-Dist: pytest_benchmark; extra == "tests"
Provides-Extra: docs
Requires-Dist: sphinx>=4; extra == "docs"
Requires-Dist: nbsphinx; extra == "docs"
Requires-Dist: ipykernel; extra == "docs"
Requires-Dist: pyvisa; extra == "docs"
Provides-Extra: plotting
Requires-Dist: matplotlib; extra == "plotting"
Provides-Extra: tabor-instruments
Requires-Dist: tabor_control>=0.1.1; extra == "tabor-instruments"
Provides-Extra: zurich-instruments
Requires-Dist: qupulse-hdawg-legacy; python_version < "3.9" and extra == "zurich-instruments"
Requires-Dist: qupulse-hdawg; python_version >= "3.9" and extra == "zurich-instruments"
Provides-Extra: faster-fractions
Requires-Dist: gmpy2; extra == "faster-fractions"
Provides-Extra: tektronix
Requires-Dist: tek_awg>=0.2.1; extra == "tektronix"
Provides-Extra: autologging
Requires-Dist: autologging; extra == "autologging"
Provides-Extra: faster-sampling
Requires-Dist: numba; extra == "faster-sampling"
Provides-Extra: default
Requires-Dist: qupulse[Faster-fractions,autologging,docs,faster-sampling,plotting,tests]; extra == "default"
Requires-Dist: pandas; extra == "default"
Dynamic: license-file
